[
	{
		"name": "Buckley Space Force Base",
		"location": "Aurora, Colorado"
	},
	{
		"name": "Los Angeles Air Force Base",
		"location": "El Segundo, California"
	},
	{
		"name": "Patrick Space Force Base",
		"location": "Brevard County, Florida"
	},
	{
		"name": "Peterson Space Force Base",
		"location": "Colorado Springs, Colorado"
	},
	{
		"name": "Schriever Space Force Base",
		"location": "Colorado Springs, Colorado"
	},
	{
		"name": "Vandenberg Space Force Base",
		"location": "Santa Barbara County, California"
	},
	{
		"name": "Cape Canaveral Space Force Station",
		"location": "Cape Canaveral, Florida"
	},
	{
		"name": "Cape Cod Space Force Station",
		"location": "Bourne, Massachusetts"
	},
	{
		"name": "Cavalier Space Force Station",
		"location": "Cavalier, North Dakota"
	},
	{
		"name": "Cheyenne Mountain Space Force Station",
		"location": "Colorado Springs, Colorado"
	},
	{
		"name": "Clear Space Force Station",
		"location": "Clear, Alaska"
	},
	{
		"name": "Kaena Point Space Force Station",
		"location": "Honolulu County, Hawaii"
	},
	{
		"name": "New Boston Space Force Station",
		"location": "New Boston, New Hampshire"
	},
	{
		"name": "Thule Air Base",
		"location": "Qaanaaq, Greenland"
	},
	{
		"name": "Kirtland Air Force Base",
		"location": "Albuquerque, New Mexico"
	},
	{
		"name": "Wright-Patterson Air Force Base",
		"location": "Dayton, Ohio"
	},
	{
		"name": "Eglin Air Force Base",
		"location": "Eglin AFB, Florida"
	},
	{
		"name": "Maxwell Air Force Base",
		"location": "Montgomery, Alabama"
	},
	{
		"name": "Beale Air Force Base",
		"location": "Marysville, California"
	},
	{
		"name": "United States Air Force Academy",
		"location": "Colorado Springs, Colorado"
	},
	{
		"name": "Nellis Air Force Base",
		"location": "Nellis AFB, Nevada"
	}
]
